pyigen/__init__.py
pyigen/files/LICENSE-for-function.txt
pyigen/files/manual.txt
pyigen-1.0.1.2.0.dist-info/METADATA
pyigen-1.0.1.2.0.dist-info/WHEEL
pyigen-1.0.1.2.0.dist-info/top_level.txt
pyigen-1.0.1.2.0.dist-info/RECORD
