Metadata-Version: 2.1
Name: pyigen
Version: 1.0.1.2.0
Summary: A package to generate a pyinstaller setup.py file!
Home-page: UNKNOWN
Author: Armaan Aggarwal
Author-email: UNKNOWN
License: UNKNOWN
Platform: UNKNOWN
Classifier: Programming Language :: Python :: 3
Classifier: License :: OSI Approved :: MIT License
Classifier: Operating System :: OS Independent
